{
  "hello": {
    "morning": "sound_001.wav",
    "day": "sound_002.wav",
    "evening": "sound_003.wav",
    "night": "sound_004.wav",
    "default": "sound_005.wav"
  },
  "goodbye": {
    "morning": "sound_006.wav",
    "day": "sound_007.wav",
    "evening": "sound_008.wav",
    "night": "sound_009.wav",
    "default": "sound_010.wav"
  },
  "search": {
    "google": "sound_011.wav",
    "wiki": "sound_012.wav",
    "youtube": "sound_013.wav",
    "wiki-not-find" : "sound_020.wav"
  },
  "translate": {
    "en-ru": "sound_014.wav",
    "ru-en": "sound_015.wav",
    "open-tab": "sound_016.wav"
  },
  "weather": {
    "today": "sound_017.wav",
    "tomorrow": "sound_018.wav",
    "open-tab": "sound_019.wav"
  },
  "applications": {
    "telegram": "sound_023.wav",
    "spotify": "sound_024.wav",
    "notepad": "sound_025.wav",
    "docs": "sound_026.wav",
    "calc": "sound_027.wav",
    "discord": "sound_028.wav"
  },
  "system-interaction": {
    "maximize-window": "sound_029.wav",
    "minimize-window": "sound_030.wav",
    "close-window": "sound_031.wav",
    "play-pause": "sound_032.wav"
  },
  "countdown": {
    "10": "sound_033.wav",
    "9": "sound_034.wav",
    "8": "sound_035.wav",
    "7": "sound_036.wav",
    "6": "sound_037.wav",
    "5": "sound_038.wav",
    "4": "sound_039.wav",
    "3": "sound_040.wav",
    "2": "sound_041.wav",
    "1": "sound_042.wav",
    "0": "sound_043.wav"
  },
  "timer": {
    "end": "sound_044.wav"
  },
  "other": {
    "thanks": "sound_021.wav",
    "notfind": "sound_022.wav"
  },
  "errors": {
    "40": {
      "44": "error_044.wav"
    },
    "50": {
      "54": "error_054.wav",
      "55": "error_055.wav"
    }
  }
}